setup.py
mongomem.egg-info/PKG-INFO
mongomem.egg-info/SOURCES.txt
mongomem.egg-info/dependency_links.txt
mongomem.egg-info/requires.txt
mongomem.egg-info/top_level.txt
src/mongomem.py
src/python-ftools/ftools.c