Metadata-Version: 1.0
Name: mongomem
Version: 0.1
Summary: A tool to analyze MongoDB memory usage by collection
Home-page: http://www.github.com/ContextLogic/mongodbtools
Author: Adam Flynn
Author-email: adam@contextlogic.com
License: MIT
Keywords: mongodb
Platform: UNKNOWN
